aws_prototyping_sdk/nx_monorepo/__init__.py
aws_prototyping_sdk/nx_monorepo/py.typed
aws_prototyping_sdk/nx_monorepo/_jsii/__init__.py
aws_prototyping_sdk/nx_monorepo/_jsii/nx-monorepo@0.19.68.jsii.tgz
aws_prototyping_sdk/nx_monorepo/nx/__init__.py
aws_prototyping_sdk.nx_monorepo-0.19.68.data/scripts/pdk-nx-dir-hasher
aws_prototyping_sdk.nx_monorepo-0.19.68.data/scripts/pdk-pnpm-link-bundled-transitive-deps
aws_prototyping_sdk.nx_monorepo-0.19.68.dist-info/LICENSE
aws_prototyping_sdk.nx_monorepo-0.19.68.dist-info/METADATA
aws_prototyping_sdk.nx_monorepo-0.19.68.dist-info/WHEEL
aws_prototyping_sdk.nx_monorepo-0.19.68.dist-info/top_level.txt
aws_prototyping_sdk.nx_monorepo-0.19.68.dist-info/RECORD
